{
    "London": {
        "Status": "ok",
        "AQI": 34,
        "Dominant pollutant": "pm25",
        "Temperature": {
            "v": 12.5
        },
        "Wind Speed": {
            "v": 0.6
        },
        "forecast": {
            "o3": {
                "avg": 4,
                "max": 14,
                "min": 1
            },
            "pm10": {
                "avg": 12,
                "max": 19,
                "min": 5
            },
            "pm25": {
                "avg": 26,
                "max": 52,
                "min": 9
            }
        }
    }
}